README.rst
setup.cfg
setup.py
JSONSchemaLibrary/__init__.py
robotframework_jsonschemalibrary.egg-info/PKG-INFO
robotframework_jsonschemalibrary.egg-info/SOURCES.txt
robotframework_jsonschemalibrary.egg-info/dependency_links.txt
robotframework_jsonschemalibrary.egg-info/entry_points.txt
robotframework_jsonschemalibrary.egg-info/not-zip-safe
robotframework_jsonschemalibrary.egg-info/requires.txt
robotframework_jsonschemalibrary.egg-info/top_level.txt