Metadata-Version: 1.1
Name: robotframework-jsonschemalibrary
Version: 1.0
Summary: A Robot Framework library for JSON Schema validation.
Home-page: https://github.com/jstaffans
Author: Johannes Staffans
Author-email: UNKNOWN
License: Apache License 2.0
Keywords: robotframework test json schema
Platform: UNKNOWN
Classifier: Development Status :: 5 - Production/Stable
Classifier: License :: OSI Approved :: Apache Software License
Classifier: Environment :: Web Environment
Classifier: Framework :: Robot Framework
Classifier: Programming Language :: Python :: 2.7
Classifier: Programming Language :: Python :: 3.5
Classifier: Programming Language :: Python :: Implementation :: CPython
